MANIFEST.in
README.rst
setup.py
aliyun_python_sdk_appmallsservice.egg-info/PKG-INFO
aliyun_python_sdk_appmallsservice.egg-info/SOURCES.txt
aliyun_python_sdk_appmallsservice.egg-info/dependency_links.txt
aliyun_python_sdk_appmallsservice.egg-info/requires.txt
aliyun_python_sdk_appmallsservice.egg-info/top_level.txt
aliyunsdkappmallsservice/__init__.py
aliyunsdkappmallsservice/endpoint.py
aliyunsdkappmallsservice/request/__init__.py
aliyunsdkappmallsservice/request/v20180224/GetMessagesRequest.py
aliyunsdkappmallsservice/request/v20180224/RemoveMessagesRequest.py
aliyunsdkappmallsservice/request/v20180224/TaobaoFilmGetCinemasRequest.py
aliyunsdkappmallsservice/request/v20180224/TaobaoFilmGetHotShowsRequest.py
aliyunsdkappmallsservice/request/v20180224/TaobaoFilmGetRegionListRequest.py
aliyunsdkappmallsservice/request/v20180224/TaobaoFilmGetSchedulesRequest.py
aliyunsdkappmallsservice/request/v20180224/TaobaoFilmGetSeatsRequest.py
aliyunsdkappmallsservice/request/v20180224/TaobaoFilmGetShowCommentsRequest.py
aliyunsdkappmallsservice/request/v20180224/TaobaoFilmGetSoonShowsRequest.py
aliyunsdkappmallsservice/request/v20180224/TaobaoFilmIssueOrderRequest.py
aliyunsdkappmallsservice/request/v20180224/TaobaoFilmLockSeatRequest.py
aliyunsdkappmallsservice/request/v20180224/TaobaoFilmUnLockSeatRequest.py
aliyunsdkappmallsservice/request/v20180224/__init__.py